apppath/__init__.py
apppath/app_path.py
apppath/app_path_utilities.py
benchmarks/__init__.py
benchmarks/benchmark_func.py
benchmarks/pqp_benchmark.py
benchmarks/returns_benchmark.py
tests/__init__.py
tests/test_nod.py
tests/test_pqp.py
tests/test_sanity.py
AppPathy-0.0.1.dist-info/LICENSE.md
AppPathy-0.0.1.dist-info/METADATA
AppPathy-0.0.1.dist-info/WHEEL
AppPathy-0.0.1.dist-info/entry_points.txt
AppPathy-0.0.1.dist-info/top_level.txt
AppPathy-0.0.1.dist-info/RECORD
