Metadata-Version: 2.1
Name: AppPathy
Version: 0.0.1
Summary: A package for easing return of multiple values
Home-page: https://github.com/cnheider/yeet
Author: Christian Heider Nielsen
Author-email: christian.heider@alexandra.dk
Maintainer: Christian Heider Nielsen
Maintainer-email: christian.heider@alexandra.dk
License: Apache License, Version 2.0
Download-URL: https://github.com/cnheider/yeet/releases
Keywords: app path paths data logs cache
Platform: UNKNOWN
Classifier: Development Status :: 4 - Beta
Classifier: Environment :: Console
Classifier: Intended Audience :: End Users/Desktop
Classifier: Intended Audience :: Developers
Classifier: License :: OSI Approved :: Apache Software License
Classifier: Operating System :: MacOS :: MacOS X
Classifier: Operating System :: Microsoft :: Windows
Classifier: Operating System :: POSIX
Classifier: Operating System :: OS Independent
Classifier: Programming Language :: Python :: 3
Classifier: Natural Language :: English
Requires-Python: >=3
Requires-Dist: numpy (>=1.16.2)
Requires-Dist: six (>=1.12.0)
Provides-Extra: all
